anystringtolower/__init__.py
anystringtolower/job.py
anystringtolower-1.0.1.dist-info/LICENCE
anystringtolower-1.0.1.dist-info/METADATA
anystringtolower-1.0.1.dist-info/WHEEL
anystringtolower-1.0.1.dist-info/top_level.txt
anystringtolower-1.0.1.dist-info/RECORD
