Metadata-Version: 2.1
Name: anystringtolower
Version: 1.0.1
Summary: Transform any string with accent and without accent to lower case
Home-page: https://github.com/VolkenoMakers/anystringtolower
Author: VOLKENO
Author-email: contact@volkeno-tank.com
License: MIT
Keywords: core package
Platform: UNKNOWN
Classifier: Development Status :: 5 - Production/Stable
Classifier: License :: OSI Approved :: MIT License
Classifier: Programming Language :: Python :: 3
Classifier: Operating System :: OS Independent
Classifier: Intended Audience :: Developers
License-File: LICENCE
Requires-Dist: anystringtolower
